SeleniumBoot/__init__.py
SeleniumBoot/boot.py
SeleniumBoot/extractor.py
SeleniumBoot/response_wrapper.py
SeleniumBoot/validator.py
SeleniumBoot-1.0.5.dist-info/METADATA
SeleniumBoot-1.0.5.dist-info/WHEEL
SeleniumBoot-1.0.5.dist-info/entry_points.txt
SeleniumBoot-1.0.5.dist-info/top_level.txt
SeleniumBoot-1.0.5.dist-info/RECORD
