Metadata-Version: 2.1
Name: SeleniumBoot
Version: 1.0.5
Summary: SeleniumBoot: make an easy way (yaml) to web automation testing
Home-page: https://github.com/shigebeyond/SeleniumBoot
Author: shigebeyond
Author-email: 772910474@qq.com
License: BSD
Classifier: Development Status :: 5 - Production/Stable
Classifier: Topic :: Software Development :: Testing
Classifier: Topic :: Software Development :: Quality Assurance
Classifier: Topic :: Software Development :: Libraries :: Python Modules
Classifier: Operating System :: POSIX :: Linux
Classifier: Operating System :: MacOS :: MacOS X
Classifier: Operating System :: Microsoft :: Windows
Classifier: Programming Language :: Python
Classifier: Programming Language :: Python :: 3.7
Classifier: Programming Language :: Python :: 3.8
Classifier: Programming Language :: Python :: 3.9
Requires-Python: >=3.6
Requires-Dist: selenium (==4.1.5)
Requires-Dist: selenium-requests (==1.4.1)
Requires-Dist: pyutilb (>=1.0.5)
